calctex/__init__.py
calctex/calc.py
calctex/common.py
calctex/constants.py
calctex/helper.py
calctex/util.py
calctex/value.py
calctex/view.py
calctex/unit/__init__.py
calctex/unit/basic.py
calctex/unit/derived.py
calctex/unit/nonsi.py
calctex/unit/scale.py
calctex/unit/unit.py
calctex-1.0.7.dist-info/METADATA
calctex-1.0.7.dist-info/WHEEL
calctex-1.0.7.dist-info/top_level.txt
calctex-1.0.7.dist-info/RECORD
