Metadata-Version: 2.1
Name: calctex
Version: 1.0.7
Summary: Show latex formula of calclation
Home-page: https://github.com/uec-world-dominators/calctex
Author: shosatojp
Author-email: me@shosato.jp
License: MIT
Keywords: calctex calc-tex calc tex latex
Platform: UNKNOWN
Classifier: License :: OSI Approved :: MIT License
Classifier: Programming Language :: Python :: 3.6
Classifier: Programming Language :: Python :: 3.7
Classifier: Programming Language :: Python :: 3.8
Requires-Python: >=3.6
Requires-Dist: numpy
